{
  "periodSnacks": {
    "categories": [
      {
        "id": "chocolate",
        "name": "Chokladterapi",
        "snacks": [
          "Mörk choklad",
          "Chokladbrownie",
          "Varm choklad med grädde",
          "Chokladglass",
          "Chokladboll",
          "Lysmelk",
          "Nutella på sked",
          "Nonstop"
        ]
      },
      {
        "id": "salty",
        "name": "Salta snacks",
        "snacks": [
          "Chips",
          "Crunchers",
          "Nachos med ost",
          "Popcorn med smör",
          "Ostbågar",
          "Nötter",
          "Saltlakrits"
        ]
      },
      {
        "id": "sweet",
        "name": "Söta frestelser",
        "snacks": [
          "Kanelbullar",
          "Glass",
          "Kakor",
          "Tårta",
          "Kladdkaka",
          "Hallongrottor"
        ]
      },
      {
        "id": "comfort",
        "name": "Tröstmat",
        "snacks": [
          "Mac and cheese",
          "Pizza",
          "Pannkakor med sylt och grädde",
          "Grilled cheese sandwich",
          "Köttbullar och potatismos",
          "Lasagne",
          "Pasta carbonara"
        ]
      },
      {
        "id": "healthyish",
        "name": "Lite nyttigare alternativ",
        "snacks": [
          "Avokadotoast",
          "Jordnötssmör på äpple",
          "Yoghurt med honung",
          "Bananskivor med choklad",
          "Smoothie bowl",
          "Nötmix",
          "Proteinbar"
        ]
      }
    ]
  },
  "cycleDayRecommendations": {
    "follikelfasen": ["healthyish", "sweet", "chocolate"],
    "ägglossningsfasen": ["salty", "chocolate"],
    "lutealfasen": ["comfort", "healthyish"]
  },
  "moodRecommendations": {
    "happy": ["sweet", "healthyish"],
    "sad": ["chocolate", "comfort", "sweet"],
    "irritated": ["salty", "chocolate", "comfort"],
    "tired": ["comfort", "chocolate", "healthyish"],
    "bloated": ["healthyish", "comfort"],
    "crampy": ["chocolate", "comfort", "salty"]
  },
  "moods": [
    {
      "id": "happy",
      "name": "Glad",
      "emoji": "😊"
    },
    {
      "id": "sad",
      "name": "Ledsen",
      "emoji": "😢"
    },
    {
      "id": "irritated",
      "name": "Irriterad",
      "emoji": "😤"
    },
    {
      "id": "tired",
      "name": "Trött",
      "emoji": "😴"
    },
    {
      "id": "bloated",
      "name": "Uppsvälld",
      "emoji": "🎈"
    },
    {
      "id": "crampy",
      "name": "Mensvärk",
      "emoji": "🤼‍♂️"
    }
  ]
}
